{
  "description": "User Management",
  "summary": "Manage user access and permissions",
  "oncall": {
    "type": "single",
    "img": "fas fa-calendar-alt",
    "urls": {
      "On-Call Schedule": {
        "url": "oncall.php",
        "roles": ["admin", "user"]
      }
    }
  },
  "dashboard": {
    "type": "single",
    "img": "fas fa-tachometer-alt",
    "urls": {
      "Dashboard": {
        "url": "index.php",
        "roles": ["admin", "user"]
      }
    }
  },
  "admin": {
    "type": "category",
    "img": "fas fa-users-cog",
    "urls": {
      "User Admin": {
        "url": "user_admin.php",
        "roles": ["admin"]
      },
      "System Logs": {
        "url": "admin_logs.php",
        "roles": ["admin"]
      }
    }
  },
  "settings": {
    "type": "category",
    "img": "fas fa-cog",
    "urls": {
      "System Settings": {
        "url": "settings.php",
        "roles": ["admin"]
      },
      "User Settings": {
        "url": "user_settings.php",
        "roles": ["admin", "user"]
      }
    }
  }
}
